Metadata-Version: 2.1
Name: request2-zlw
Version: 0.5
Summary: Módulo para exemplificar construção de projetos Python no curso PyTools
Home-page: https://github.com/zlwzlw66/requestzlw
Author: Raphael Moral
Author-email: 1947340072@qq.com
License: GNU AFFERO GENERAL PUBLIC LICENSE
Project-URL: Source, https://github.com/zlwzlw66/requestzlw
Project-URL: Documentation, https://github.com/zlwzlw66/requestzlw/latest
Project-URL: Tracker, https://github.com/zlwzlw66/requestzlw/issues
Classifier: Development Status :: 2 - Pre-Alpha
Classifier: Environment :: Console
Classifier: Intended Audience :: Developers
Classifier: License :: OSI Approved :: GNU Affero General Public License v3 or later (AGPLv3+)
Classifier: Operating System :: OS Independent
Classifier: Programming Language :: Python
Classifier: Programming Language :: Python :: 3.6
Classifier: Framework :: Pytest
Requires-Dist: requests
